MANIFEST.in
README.md
setup.cfg
setup.py
FUTIL/__init__.py
FUTIL/mails.py
FUTIL/my_logging.py
FUTIL.egg-info/PKG-INFO
FUTIL.egg-info/SOURCES.txt
FUTIL.egg-info/dependency_links.txt
FUTIL.egg-info/top_level.txt
test/test.py