Metadata-Version: 1.1
Name: FUTIL
Version: 0.1.5
Summary: A personal librairy with utils
Home-page: UNKNOWN
Author: FredThx
Author-email: FredThx@gmail.com
License: WTFPL
Platform: UNKNOWN
Classifier: Programming Language :: Python
Classifier: Development Status :: 4 - Beta
Classifier: License :: OSI Approved
Classifier: Natural Language :: French
Classifier: Operating System :: OS Independent
Classifier: Programming Language :: Python :: 2.7
